<?xml version="1.0" encoding="UTF-8"?><record_update table="sp_instance_table">
    <sp_instance_table action="INSERT_OR_UPDATE">
        <active>true</active>
        <class_name/>
        <color>default</color>
        <css/>
        <display_field/>
        <field_list/>
        <filter/>
        <glyph/>
        <id/>
        <maximum_entries>5</maximum_entries>
        <order>1</order>
        <order_by/>
        <order_direction>asc</order_direction>
        <roles/>
        <short_description/>
        <size>md</size>
        <sp_column display_value="1">190cfee0833bc210c2f1f0b6feaad349</sp_column>
        <sp_page display_value="form">ed5f8ec347730200ba13a5554ee49046</sp_page>
        <sp_widget display_value="Data Table - Instance Definition Wrapper">4ec37dae77c20110d3ef07dc7d5a997b</sp_widget>
        <sys_class_name>sp_instance_table</sys_class_name>
        <sys_created_by>admin</sys_created_by>
        <sys_created_on>2024-08-04 19:39:27</sys_created_on>
        <sys_id>88f10c8a83f78a10c2f1f0b6feaad355</sys_id>
        <sys_mod_count>1</sys_mod_count>
        <sys_name/>
        <sys_package display_value="Aqua Power" source="x_1346722_magma">24240a5f83af0a10c2f1f0b6feaad317</sys_package>
        <sys_policy/>
        <sys_scope display_value="Aqua Power">24240a5f83af0a10c2f1f0b6feaad317</sys_scope>
        <sys_update_name>sp_instance_table_88f10c8a83f78a10c2f1f0b6feaad355</sys_update_name>
        <sys_updated_by>admin</sys_updated_by>
        <sys_updated_on>2024-08-04 19:39:57</sys_updated_on>
        <table>x_1346722_magma_request_details</table>
        <title/>
        <url/>
        <widget_parameters/>
    </sp_instance_table>
    <sys_translated_text action="delete_multiple" query="documentkey=88f10c8a83f78a10c2f1f0b6feaad355"/>
</record_update>
